{"id":"285712","name":"王牌投手 振臂高揮 夏季大會篇","count":14,"episodes":[{"label":"第01集","url":"https://gimyai.tw/play/285712-2-1.html"},{"label":"第02集","url":"https://gimyai.tw/play/285712-2-2.html"},{"label":"第03集","url":"https://gimyai.tw/play/285712-2-3.html"},{"label":"第04集","url":"https://gimyai.tw/play/285712-2-4.html"},{"label":"第05集","url":"https://gimyai.tw/play/285712-2-5.html"},{"label":"第06集","url":"https://gimyai.tw/play/285712-2-6.html"},{"label":"第07集","url":"https://gimyai.tw/play/285712-2-7.html"},{"label":"第08集","url":"https://gimyai.tw/play/285712-2-8.html"},{"label":"第09集","url":"https://gimyai.tw/play/285712-2-9.html"},{"label":"第10集","url":"https://gimyai.tw/play/285712-2-10.html"},{"label":"第11集","url":"https://gimyai.tw/play/285712-2-11.html"},{"label":"第12集","url":"https://gimyai.tw/play/285712-2-12.html"},{"label":"第12.5集","url":"https://gimyai.tw/play/285712-2-13.html"},{"label":"第13集","url":"https://gimyai.tw/play/285712-2-14.html"}]}