{"id":"344230","name":"神墓 年番","count":50,"episodes":[{"label":"第01集","url":"https://gimyai.tw/play/344230-9-1.html"},{"label":"第02集","url":"https://gimyai.tw/play/344230-9-2.html"},{"label":"第03集","url":"https://gimyai.tw/play/344230-9-3.html"},{"label":"第04集","url":"https://gimyai.tw/play/344230-9-4.html"},{"label":"第05集","url":"https://gimyai.tw/play/344230-9-5.html"},{"label":"第06集","url":"https://gimyai.tw/play/344230-9-6.html"},{"label":"第07集","url":"https://gimyai.tw/play/344230-9-7.html"},{"label":"第08集","url":"https://gimyai.tw/play/344230-9-8.html"},{"label":"第09集","url":"https://gimyai.tw/play/344230-9-9.html"},{"label":"第10集","url":"https://gimyai.tw/play/344230-9-10.html"},{"label":"第11集","url":"https://gimyai.tw/play/344230-9-11.html"},{"label":"第12集","url":"https://gimyai.tw/play/344230-9-12.html"},{"label":"第13集","url":"https://gimyai.tw/play/344230-9-13.html"},{"label":"第14集","url":"https://gimyai.tw/play/344230-9-14.html"},{"label":"第15集","url":"https://gimyai.tw/play/344230-9-15.html"},{"label":"第16集","url":"https://gimyai.tw/play/344230-9-16.html"},{"label":"第17集","url":"https://gimyai.tw/play/344230-9-17.html"},{"label":"第18集","url":"https://gimyai.tw/play/344230-9-18.html"},{"label":"第19集","url":"https://gimyai.tw/play/344230-9-19.html"},{"label":"第20集","url":"https://gimyai.tw/play/344230-9-20.html"},{"label":"第21集","url":"https://gimyai.tw/play/344230-9-21.html"},{"label":"第22集","url":"https://gimyai.tw/play/344230-9-22.html"},{"label":"第23集","url":"https://gimyai.tw/play/344230-9-23.html"},{"label":"第24集","url":"https://gimyai.tw/play/344230-9-24.html"},{"label":"第25集","url":"https://gimyai.tw/play/344230-9-25.html"},{"label":"第26集","url":"https://gimyai.tw/play/344230-9-26.html"},{"label":"第27集","url":"https://gimyai.tw/play/344230-9-27.html"},{"label":"第28集","url":"https://gimyai.tw/play/344230-9-28.html"},{"label":"第29集","url":"https://gimyai.tw/play/344230-9-29.html"},{"label":"第30集","url":"https://gimyai.tw/play/344230-9-30.html"},{"label":"第31集","url":"https://gimyai.tw/play/344230-9-31.html"},{"label":"第32集","url":"https://gimyai.tw/play/344230-9-32.html"},{"label":"第33集","url":"https://gimyai.tw/play/344230-9-33.html"},{"label":"第34集","url":"https://gimyai.tw/play/344230-9-34.html"},{"label":"第35集","url":"https://gimyai.tw/play/344230-9-35.html"},{"label":"第36集","url":"https://gimyai.tw/play/344230-9-36.html"},{"label":"第37集","url":"https://gimyai.tw/play/344230-9-37.html"},{"label":"第38集","url":"https://gimyai.tw/play/344230-9-38.html"},{"label":"第39集","url":"https://gimyai.tw/play/344230-9-39.html"},{"label":"第40集","url":"https://gimyai.tw/play/344230-9-40.html"},{"label":"第41集","url":"https://gimyai.tw/play/344230-9-41.html"},{"label":"第42集","url":"https://gimyai.tw/play/344230-9-42.html"},{"label":"第43集","url":"https://gimyai.tw/play/344230-9-43.html"},{"label":"第44集","url":"https://gimyai.tw/play/344230-9-44.html"},{"label":"第45集","url":"https://gimyai.tw/play/344230-9-45.html"},{"label":"第46集","url":"https://gimyai.tw/play/344230-9-46.html"},{"label":"第47集","url":"https://gimyai.tw/play/344230-9-47.html"},{"label":"第48集","url":"https://gimyai.tw/play/344230-9-48.html"},{"label":"第49集","url":"https://gimyai.tw/play/344230-9-49.html"},{"label":"第50集","url":"https://gimyai.tw/play/344230-9-50.html"}]}