{"id":"432221","name":"無限超越班第四季","count":93,"episodes":[{"label":"20260328","url":"https://gimyai.tw/play/432221-2-1.html"},{"label":"20260328","url":"https://gimyai.tw/play/432221-2-2.html"},{"label":"20260404","url":"https://gimyai.tw/play/432221-2-3.html"},{"label":"20260404","url":"https://gimyai.tw/play/432221-2-4.html"},{"label":"20260404","url":"https://gimyai.tw/play/432221-2-5.html"},{"label":"20260405","url":"https://gimyai.tw/play/432221-2-6.html"},{"label":"20260411","url":"https://gimyai.tw/play/432221-2-7.html"},{"label":"20260411","url":"https://gimyai.tw/play/432221-2-8.html"},{"label":"20260411","url":"https://gimyai.tw/play/432221-2-9.html"},{"label":"20260411","url":"https://gimyai.tw/play/432221-2-10.html"},{"label":"20260412","url":"https://gimyai.tw/play/432221-2-11.html"},{"label":"20260418","url":"https://gimyai.tw/play/432221-2-12.html"},{"label":"20260418","url":"https://gimyai.tw/play/432221-2-13.html"},{"label":"20260418","url":"https://gimyai.tw/play/432221-2-14.html"},{"label":"20260418","url":"https://gimyai.tw/play/432221-2-15.html"},{"label":"20260418","url":"https://gimyai.tw/play/432221-2-16.html"},{"label":"20260419","url":"https://gimyai.tw/play/432221-2-17.html"},{"label":"20260419","url":"https://gimyai.tw/play/432221-2-18.html"},{"label":"20260419","url":"https://gimyai.tw/play/432221-2-19.html"},{"label":"20260425","url":"https://gimyai.tw/play/432221-2-20.html"},{"label":"20260425","url":"https://gimyai.tw/play/432221-2-21.html"},{"label":"20260425","url":"https://gimyai.tw/play/432221-2-22.html"},{"label":"20260426","url":"https://gimyai.tw/play/432221-2-23.html"},{"label":"20260426","url":"https://gimyai.tw/play/432221-2-24.html"},{"label":"20260428","url":"https://gimyai.tw/play/432221-2-25.html"},{"label":"20260502","url":"https://gimyai.tw/play/432221-2-26.html"},{"label":"20260502","url":"https://gimyai.tw/play/432221-2-27.html"},{"label":"20260502","url":"https://gimyai.tw/play/432221-2-28.html"},{"label":"20260503","url":"https://gimyai.tw/play/432221-2-29.html"},{"label":"20260503","url":"https://gimyai.tw/play/432221-2-30.html"},{"label":"20260504","url":"https://gimyai.tw/play/432221-2-31.html"},{"label":"20260504","url":"https://gimyai.tw/play/432221-2-32.html"},{"label":"20260509","url":"https://gimyai.tw/play/432221-2-33.html"},{"label":"20260509","url":"https://gimyai.tw/play/432221-2-34.html"},{"label":"20260509","url":"https://gimyai.tw/play/432221-2-35.html"},{"label":"20260510","url":"https://gimyai.tw/play/432221-2-36.html"},{"label":"20260510","url":"https://gimyai.tw/play/432221-2-37.html"},{"label":"20260511","url":"https://gimyai.tw/play/432221-2-38.html"},{"label":"20260511","url":"https://gimyai.tw/play/432221-2-39.html"},{"label":"20260516","url":"https://gimyai.tw/play/432221-2-40.html"},{"label":"20260516","url":"https://gimyai.tw/play/432221-2-41.html"},{"label":"20260516","url":"https://gimyai.tw/play/432221-2-42.html"},{"label":"20260516","url":"https://gimyai.tw/play/432221-2-43.html"},{"label":"20260517","url":"https://gimyai.tw/play/432221-2-44.html"},{"label":"20260517","url":"https://gimyai.tw/play/432221-2-45.html"},{"label":"20260518","url":"https://gimyai.tw/play/432221-2-46.html"},{"label":"20260519","url":"https://gimyai.tw/play/432221-2-47.html"},{"label":"20260523","url":"https://gimyai.tw/play/432221-2-48.html"},{"label":"20260523","url":"https://gimyai.tw/play/432221-2-49.html"},{"label":"20260523","url":"https://gimyai.tw/play/432221-2-50.html"},{"label":"20260523","url":"https://gimyai.tw/play/432221-2-51.html"},{"label":"20260524","url":"https://gimyai.tw/play/432221-2-52.html"},{"label":"20260524","url":"https://gimyai.tw/play/432221-2-53.html"},{"label":"20260526","url":"https://gimyai.tw/play/432221-2-54.html"},{"label":"20260528","url":"https://gimyai.tw/play/432221-2-55.html"},{"label":"20260530","url":"https://gimyai.tw/play/432221-2-56.html"},{"label":"20260530","url":"https://gimyai.tw/play/432221-2-57.html"},{"label":"20260530","url":"https://gimyai.tw/play/432221-2-58.html"},{"label":"20260530","url":"https://gimyai.tw/play/432221-2-59.html"},{"label":"20260531","url":"https://gimyai.tw/play/432221-2-60.html"},{"label":"20260531","url":"https://gimyai.tw/play/432221-2-61.html"},{"label":"20260601","url":"https://gimyai.tw/play/432221-2-62.html"},{"label":"20260601","url":"https://gimyai.tw/play/432221-2-63.html"},{"label":"20260601","url":"https://gimyai.tw/play/432221-2-64.html"},{"label":"20260602","url":"https://gimyai.tw/play/432221-2-65.html"},{"label":"20260606","url":"https://gimyai.tw/play/432221-2-66.html"},{"label":"20260606","url":"https://gimyai.tw/play/432221-2-67.html"},{"label":"20260606","url":"https://gimyai.tw/play/432221-2-68.html"},{"label":"20260606","url":"https://gimyai.tw/play/432221-2-69.html"},{"label":"20260607","url":"https://gimyai.tw/play/432221-2-70.html"},{"label":"20260607","url":"https://gimyai.tw/play/432221-2-71.html"},{"label":"20260608","url":"https://gimyai.tw/play/432221-2-72.html"},{"label":"20260608","url":"https://gimyai.tw/play/432221-2-73.html"},{"label":"20260609","url":"https://gimyai.tw/play/432221-2-74.html"},{"label":"20260611","url":"https://gimyai.tw/play/432221-2-75.html"},{"label":"20260613","url":"https://gimyai.tw/play/432221-2-76.html"},{"label":"20260613","url":"https://gimyai.tw/play/432221-2-77.html"},{"label":"20260613","url":"https://gimyai.tw/play/432221-2-78.html"},{"label":"20260613","url":"https://gimyai.tw/play/432221-2-79.html"},{"label":"20260613","url":"https://gimyai.tw/play/432221-2-80.html"},{"label":"20260613","url":"https://gimyai.tw/play/432221-2-81.html"},{"label":"20260613","url":"https://gimyai.tw/play/432221-2-82.html"},{"label":"20260613","url":"https://gimyai.tw/play/432221-2-83.html"},{"label":"20260614","url":"https://gimyai.tw/play/432221-2-84.html"},{"label":"20260615","url":"https://gimyai.tw/play/432221-2-85.html"},{"label":"20260616","url":"https://gimyai.tw/play/432221-2-86.html"},{"label":"20260618","url":"https://gimyai.tw/play/432221-2-87.html"},{"label":"20260620","url":"https://gimyai.tw/play/432221-2-88.html"},{"label":"20260621","url":"https://gimyai.tw/play/432221-2-89.html"},{"label":"20260622","url":"https://gimyai.tw/play/432221-2-90.html"},{"label":"20260623","url":"https://gimyai.tw/play/432221-2-91.html"},{"label":"20260625","url":"https://gimyai.tw/play/432221-2-92.html"},{"label":"20260627","url":"https://gimyai.tw/play/432221-2-93.html"}]}